dwho/__init__.py
dwho/config.py
dwho/adapters/__init__.py
dwho/adapters/redis.py
dwho/classes/__init__.py
dwho/classes/abstract.py
dwho/classes/errors.py
dwho/classes/inoplugs.py
dwho/classes/inotify.py
dwho/classes/libloader.py
dwho/classes/modules.py
dwho/classes/notifiers.py
dwho/classes/objects.py
dwho/classes/plugins.py
dwho/helpers/__init__.py
dwho/helpers/crypto.py
dwho/modules/__init__.py
dwho/modules/web.py
dwho/plugins/__init__.py
dwho-0.3.59.dist-info/LICENSE
dwho-0.3.59.dist-info/METADATA
dwho-0.3.59.dist-info/WHEEL
dwho-0.3.59.dist-info/top_level.txt
dwho-0.3.59.dist-info/RECORD
